{
  "id": "components/banner/index",
  "title": "Banner",
  "description": "Displays announcements at the top of pages for urgent communications",
  "source": "@site/docs/components/banner/index.mdx",
  "sourceDirName": "components/banner",
  "slug": "/components/banner/",
  "permalink": "/docs/components/banner/",
  "draft": false,
  "unlisted": false,
  "editUrl": "http://localhost:3000/admin/#/collections/components/entries/banner/index",
  "tags": [],
  "version": "current",
  "frontMatter": {
    "cms_editable": true,
    "title": "Banner",
    "description": "Displays announcements at the top of pages for urgent communications",
    "maturity": "deployed",
    "platforms": [
      "web"
    ],
    "github": "https://github.com/department-of-veterans-affairs/vets-design-system-documentation/issues?q=is%3Aissue+is%3Aopen+label%3Ava-banner",
    "figma": "https://www.figma.com/file/JDFpGLIojfuQwANXScQjqe/VADS-Component-Library?type=design",
    "storybook": "https://design.va.gov/storybook/?path=/docs/uswds-va-banner--docs",
    "research": "https://github.com/department-of-veterans-affairs/va.gov-research-repository/issues?q=is%3Aissue+label%3A%22DSC%3A+Banner%22",
    "variations": [
      {
        "name": "Banner - Maintenance",
        "url": "./maintenance",
        "description": "For system maintenance notifications"
      },
      {
        "name": "Banner - Official Gov",
        "url": "./official-gov",
        "description": "Identifies official government websites"
      }
    ],
    "related": [
      {
        "name": "Alert",
        "url": "/docs/components/alert/",
        "description": "For user feedback and system messages"
      }
    ],
    "usage": {
      "when_to_use": [
        {
          "value": "**Emergency communications:** Government shutdowns or critical VA service disruptions"
        },
        {
          "value": "**Facility-related notices:** Hours changes, construction, weather alerts, closures, utility outages"
        },
        {
          "value": "**Veteran actions required:** IRS deadlines, notification sign-ups"
        }
      ],
      "when_to_consider_else": [
        {
          "value": "**Alert component:** User feedback, system messages, engagement notifications"
        },
        {
          "value": "**Banner - Maintenance:** Scheduled downtime announcements"
        },
        {
          "value": "**CMS components:** Health-related promotions, events, news releases"
        }
      ]
    },
    "content_considerations": [
      {
        "value": "Maximum 70 characters (with spaces)"
      },
      {
        "value": "Scan-friendly, eliminate unnecessary detail"
      },
      {
        "value": "Maximum 300 characters (with spaces)"
      },
      {
        "value": "Link to detail pages for additional information"
      }
    ],
    "examples": [
      {
        "title": "Info banner",
        "description": "Info banner",
        "storyId": "uswds-va-banner--default",
        "height": 150
      },
      {
        "title": "Warning banner",
        "description": "Warning banner",
        "storyId": "uswds-va-banner--warning",
        "height": 150
      }
    ],
    "code_usage": "<va-banner\n  headline=\"Important announcement\"\n  type=\"info\"\n  show-close\n>\n  <p>Banner content with <a href=\"/details\">more details</a>.</p>\n</va-banner>\n",
    "component_tag": "va-banner"
  },
  "sidebar": "componentsSidebar",
  "previous": {
    "title": "Back to top",
    "permalink": "/docs/components/back-to-top/"
  },
  "next": {
    "title": "Banner - Maintenance",
    "permalink": "/docs/components/banner/maintenance/"
  }
}